shardai/__init__.py
shardai/chat.py
shardai/client.py
shardai/exceptions.py
shardai/image.py
shardai/moderation.py
shardai/objects.py
shardai/tts.py
shardai-0.0.5.dist-info/METADATA
shardai-0.0.5.dist-info/WHEEL
shardai-0.0.5.dist-info/licenses/LICENSE
shardai-0.0.5.dist-info/RECORD
