Metadata-Version: 2.1
Name: shardai
Version: 0.0.5
Summary: A package for ShardAI
Project-URL: Homepage, https://github.com/Puzzy124/shard-api-client
Project-URL: Issues, https://github.com/Puzzy124/shard-api-client/issues
Author-email: Puzzy124 <contact@shard-ai.xyz>, QuartzWarrior <contact@quartzwarrior.xyz>
License-File: LICENSE
Classifier: License :: OSI Approved :: MIT License
Classifier: Operating System :: OS Independent
Classifier: Programming Language :: Python :: 3
Requires-Python: >=3.8
